Toolkit/__init__.py
Toolkit/_collib.py
Toolkit/_glue.py
Toolkit/_pionier.py
Toolkit/audio.py
Toolkit/errors.py
Toolkit/examples.py
Toolkit/image.py
Toolkit/parse.py
Toolkit/tracking.py
tkt_Toolkit-2.0.dist-info/METADATA
tkt_Toolkit-2.0.dist-info/WHEEL
tkt_Toolkit-2.0.dist-info/license
tkt_Toolkit-2.0.dist-info/top_level.txt
tkt_Toolkit-2.0.dist-info/RECORD
