Metadata-Version: 2.1
Name: tkt-Toolkit
Version: 2.0
Summary: Useful collection of python packages and scripts.
Home-page: https://github.com/MOBSkuchen/tkt-Toolkit
Author: Suprime
Author-email: suprime.sendings@gmail.com
License: MIT
Classifier: Programming Language :: Python :: 3
Classifier: License :: OSI Approved :: MIT License
Classifier: Operating System :: OS Independent
Requires-Python: >=3.7
License-File: license
Requires-Dist: httpx
Requires-Dist: googletrans (==3.1.0a0)
Requires-Dist: SpeechRecognition
Requires-Dist: termcolor
Requires-Dist: keyboard
Requires-Dist: piexif
Requires-Dist: pydub
Requires-Dist: pygame
Requires-Dist: pywin32
